eb7calculator/__init__.py
eb7calculator/calculator.py
eb7calculator-0.0.1.dist-info/METADATA
eb7calculator-0.0.1.dist-info/WHEEL
eb7calculator-0.0.1.dist-info/top_level.txt
eb7calculator-0.0.1.dist-info/RECORD
