Metadata-Version: 2.1
Name: eb7calculator
Version: 0.0.1
Summary: A simple calculator
Home-page: https://github.com/birnesh/eb7calculator
Author: Birnesh Eswaramoorthy
Author-email: birnesh1996@gmail.com
License: MIT
Keywords: python,calc,calculator,cal,simple,basic
Platform: UNKNOWN
Classifier: License :: OSI Approved :: MIT License
Classifier: Programming Language :: Python :: 3
Classifier: Programming Language :: Python :: 3.7
